kedro_aim/__init__.py
kedro_aim/aim/__init__.py
kedro_aim/aim/utils.py
kedro_aim/config/__init__.py
kedro_aim/config/model.py
kedro_aim/config/utils.py
kedro_aim/framework/__init__.py
kedro_aim/framework/cli/__init__.py
kedro_aim/framework/cli/cli.py
kedro_aim/framework/cli/cli_utils.py
kedro_aim/framework/hooks/__init__.py
kedro_aim/framework/hooks/aim_hook.py
kedro_aim/framework/hooks/utils.py
kedro_aim/io/__init__.py
kedro_aim/io/artifacts/__init__.py
kedro_aim/io/artifacts/aim_artifact_dataset.py
kedro_aim/template/__init__.py
kedro_aim/template/config/aim.yml
kedro_aim-0.1.3.dist-info/entry_points.txt
kedro_aim-0.1.3.dist-info/LICENSE
kedro_aim-0.1.3.dist-info/WHEEL
kedro_aim-0.1.3.dist-info/METADATA
kedro_aim-0.1.3.dist-info/RECORD
