Metadata-Version: 2.1
Name: kedro-aim
Version: 0.1.3
Summary: A plugin to integrate the mlops plattform aim into your kedro project
Home-page: https://kedro-aim.readthedocs.io
License: MIT
Keywords: kedro,aim,kedro-plugin
Author: An Hoang
Author-email: anhoang31415@gmail.com
Requires-Python: >=3.8,<3.11
Classifier: Development Status :: 4 - Beta
Classifier: Environment :: Plugins
Classifier: Framework :: Kedro
Classifier: Intended Audience :: Developers
Classifier: License :: OSI Approved :: MIT License
Classifier: Operating System :: MacOS
Classifier: Operating System :: Microsoft :: Windows
Classifier: Operating System :: POSIX :: Linux
Classifier: Programming Language :: Python :: 3
Classifier: Programming Language :: Python :: 3.8
Classifier: Programming Language :: Python :: 3.9
Classifier: Programming Language :: Python :: 3.10
Classifier: Programming Language :: Python :: 3.10
Classifier: Programming Language :: Python :: 3.7
Classifier: Programming Language :: Python :: 3.8
Classifier: Programming Language :: Python :: 3.9
Requires-Dist: aim (>=3.14.1,<4.0.0)
Requires-Dist: kedro (>=0.18.0)
Requires-Dist: pydantic (>=1.10.2,<2.0.0)
Project-URL: Documentation, https://kedro-aim.readthedocs.io
Project-URL: Repository, https://github.com/AnH0ang/kedro-aim
